<?xml version="1.0" encoding="UTF-8"?>
<java version="18.0.1.1" class="java.beans.XMLDecoder">
 <object class="co.edu.uniquindio.progiii.subastasquindio.model.CasaSubastas" id="CasaSubastas0">
  <void property="listaPublicaciones">
   <void method="add">
    <object class="co.edu.uniquindio.progiii.subastasquindio.model.Publicacion" id="Publicacion0">
     <void property="articulo">
      <object class="co.edu.uniquindio.progiii.subastasquindio.model.Articulo" id="Articulo0">
       <void property="descripcion">
        <string>Es un arroz</string>
       </void>
       <void property="nombre">
        <string>Arroz</string>
       </void>
       <void property="tipo">
        <object class="java.lang.Enum" id="TipoPublicacion0" method="valueOf">
         <class>co.edu.uniquindio.progiii.subastasquindio.model.TipoPublicacion</class>
         <string>DEPORTES</string>
        </object>
       </void>
       <void property="vendedor">
        <object class="co.edu.uniquindio.progiii.subastasquindio.model.Vendedor" id="Vendedor0">
         <void property="articulos">
          <void method="add">
           <object class="co.edu.uniquindio.progiii.subastasquindio.model.Articulo">
            <void property="descripcion">
             <string>Es un pan</string>
            </void>
            <void property="nombre">
             <string>Pan</string>
            </void>
            <void property="tipo">
             <object idref="TipoPublicacion0"/>
            </void>
            <void property="vendedor">
             <object idref="Vendedor0"/>
            </void>
           </object>
          </void>
          <void method="add">
           <object idref="Articulo0"/>
          </void>
          <void method="add">
           <object class="co.edu.uniquindio.progiii.subastasquindio.model.Articulo" id="Articulo1">
            <void property="descripcion">
             <string>Es un sapo</string>
            </void>
            <void property="nombre">
             <string>Sapo</string>
            </void>
            <void property="tipo">
             <object class="java.lang.Enum" id="TipoPublicacion1" method="valueOf">
              <class>co.edu.uniquindio.progiii.subastasquindio.model.TipoPublicacion</class>
              <string>HOGAR</string>
             </object>
            </void>
            <void property="vendedor">
             <object idref="Vendedor0"/>
            </void>
           </object>
          </void>
          <void method="add">
           <object class="co.edu.uniquindio.progiii.subastasquindio.model.Articulo" id="Articulo2">
            <void property="descripcion">
             <string>Es un chechere</string>
            </void>
            <void property="nombre">
             <string>Chayomi</string>
            </void>
            <void property="tipo">
             <object idref="TipoPublicacion0"/>
            </void>
            <void property="vendedor">
             <object idref="Vendedor0"/>
            </void>
           </object>
          </void>
          <void method="add">
           <object class="co.edu.uniquindio.progiii.subastasquindio.model.Articulo" id="Articulo3">
            <void property="descripcion">
             <string>Es un samsing</string>
            </void>
            <void property="nombre">
             <string>Samsung</string>
            </void>
            <void property="tipo">
             <object idref="TipoPublicacion1"/>
            </void>
            <void property="vendedor">
             <object idref="Vendedor0"/>
            </void>
           </object>
          </void>
          <void method="add">
           <object class="co.edu.uniquindio.progiii.subastasquindio.model.Articulo" id="Articulo4">
            <void property="descripcion">
             <string>Es una casa grande de dos pisos con piscina incluida</string>
            </void>
            <void property="nombre">
             <string>Casa Grande</string>
            </void>
            <void property="tipo">
             <object class="java.lang.Enum" id="TipoPublicacion2" method="valueOf">
              <class>co.edu.uniquindio.progiii.subastasquindio.model.TipoPublicacion</class>
              <string>BIEN_RAIZ</string>
             </object>
            </void>
            <void property="vendedor">
             <object idref="Vendedor0"/>
            </void>
           </object>
          </void>
          <void method="add">
           <object class="co.edu.uniquindio.progiii.subastasquindio.model.Articulo">
            <void property="descripcion">
             <string>esto es una prueba</string>
            </void>
            <void property="nombre">
             <string>Prueba1</string>
            </void>
            <void property="tipo">
             <object class="java.lang.Enum" id="TipoPublicacion3" method="valueOf">
              <class>co.edu.uniquindio.progiii.subastasquindio.model.TipoPublicacion</class>
              <string>VEHICULOS</string>
             </object>
            </void>
            <void property="vendedor">
             <object idref="Vendedor0"/>
            </void>
           </object>
          </void>
          <void method="add">
           <object class="co.edu.uniquindio.progiii.subastasquindio.model.Articulo">
            <void property="descripcion">
             <string>adg</string>
            </void>
            <void property="nombre">
             <string>Prueba2</string>
            </void>
            <void property="tipo">
             <object idref="TipoPublicacion3"/>
            </void>
            <void property="vendedor">
             <object idref="Vendedor0"/>
            </void>
           </object>
          </void>
          <void method="add">
           <object class="co.edu.uniquindio.progiii.subastasquindio.model.Articulo">
            <void property="descripcion">
             <string>tujrdtgj</string>
            </void>
            <void property="nombre">
             <string>Prueba3</string>
            </void>
            <void property="tipo">
             <object class="java.lang.Enum" id="TipoPublicacion4" method="valueOf">
              <class>co.edu.uniquindio.progiii.subastasquindio.model.TipoPublicacion</class>
              <string>TECNOLOGIA</string>
             </object>
            </void>
            <void property="vendedor">
             <object idref="Vendedor0"/>
            </void>
           </object>
          </void>
         </void>
         <void property="contrasena">
          <string>1234</string>
         </void>
         <void property="edad">
          <int>15</int>
         </void>
         <void property="email">
          <string>josh@mail.com</string>
         </void>
         <void property="id">
          <string>1234</string>
         </void>
         <void property="nombreUsuario">
          <string>JoshSell</string>
         </void>
         <void property="publicaciones">
          <void method="add">
           <object class="co.edu.uniquindio.progiii.subastasquindio.model.Publicacion">
            <void property="articulo">
             <object idref="Articulo3"/>
            </void>
            <void property="estado">
             <object class="java.lang.Enum" id="Estado0" method="valueOf">
              <class>co.edu.uniquindio.progiii.subastasquindio.model.Estado</class>
              <string>VENDIDO</string>
             </object>
            </void>
            <void property="valorInicial">
             <int>13</int>
            </void>
           </object>
          </void>
          <void method="add">
           <object class="co.edu.uniquindio.progiii.subastasquindio.model.Publicacion" id="Publicacion1">
            <void property="articulo">
             <object class="co.edu.uniquindio.progiii.subastasquindio.model.Articulo">
              <void property="descripcion">
               <string>Es una arepa artesanal</string>
              </void>
              <void property="foto">
               <string>/Users/nicolasjurado/Library/CloudStorage/OneDrive-Personal/Fotos NutriArepa/DSC_0046 copy.jpg</string>
              </void>
              <void property="nombre">
               <string>Arepa</string>
              </void>
              <void property="tipo">
               <object idref="TipoPublicacion1"/>
              </void>
              <void property="vendedor">
               <object idref="Vendedor0"/>
              </void>
             </object>
            </void>
            <void property="estado">
             <object idref="Estado0"/>
            </void>
            <void property="pujaGanadora">
             <object class="co.edu.uniquindio.progiii.subastasquindio.model.Puja" id="Puja0">
              <void property="comprador">
               <object class="co.edu.uniquindio.progiii.subastasquindio.model.Comprador" id="Comprador0">
                <void property="contrasena">
                 <string>1234</string>
                </void>
                <void property="edad">
                 <int>19</int>
                </void>
                <void property="email">
                 <string>comprador@mail.com</string>
                </void>
                <void property="nombreUsuario">
                 <string>CompradorTest1</string>
                </void>
                <void property="pujas">
                 <void method="add">
                  <object class="co.edu.uniquindio.progiii.subastasquindio.model.Puja" id="Puja1">
                   <void property="comprador">
                    <object idref="Comprador0"/>
                   </void>
                   <void property="dineroOfrecido">
                    <int>1</int>
                   </void>
                   <void property="publicacion">
                    <object class="co.edu.uniquindio.progiii.subastasquindio.model.Publicacion" id="Publicacion2">
                     <void property="articulo">
                      <object class="co.edu.uniquindio.progiii.subastasquindio.model.Articulo">
                       <void property="descripcion">
                        <string>Es una arepa artesanal</string>
                       </void>
                       <void property="foto">
                        <string>/Users/nicolasjurado/Library/CloudStorage/OneDrive-Personal/Fotos NutriArepa/DSC_0046 copy.jpg</string>
                       </void>
                       <void property="nombre">
                        <string>ArepaOK</string>
                       </void>
                       <void property="tipo">
                        <object idref="TipoPublicacion1"/>
                       </void>
                       <void property="vendedor">
                        <object idref="Vendedor0"/>
                       </void>
                      </object>
                     </void>
                     <void property="estado">
                      <object class="java.lang.Enum" id="Estado1" method="valueOf">
                       <class>co.edu.uniquindio.progiii.subastasquindio.model.Estado</class>
                       <string>ACTIVO</string>
                      </object>
                     </void>
                     <void property="pujas">
                      <void method="add">
                       <object idref="Puja1"/>
                      </void>
                      <void method="add">
                       <object class="co.edu.uniquindio.progiii.subastasquindio.model.Puja" id="Puja2">
                        <void property="comprador">
                         <object idref="Comprador0"/>
                        </void>
                        <void property="dineroOfrecido">
                         <int>13</int>
                        </void>
                        <void property="publicacion">
                         <object idref="Publicacion2"/>
                        </void>
                       </object>
                      </void>
                     </void>
                     <void property="valorInicial">
                      <int>10999</int>
                     </void>
                    </object>
                   </void>
                  </object>
                 </void>
                 <void method="add">
                  <object idref="Puja2"/>
                 </void>
                 <void method="add">
                  <object class="co.edu.uniquindio.progiii.subastasquindio.model.Puja" id="Puja3">
                   <void property="comprador">
                    <object idref="Comprador0"/>
                   </void>
                   <void property="dineroOfrecido">
                    <int>1</int>
                   </void>
                   <void property="publicacion">
                    <object idref="Publicacion1"/>
                   </void>
                  </object>
                 </void>
                 <void method="add">
                  <object class="co.edu.uniquindio.progiii.subastasquindio.model.Puja" id="Puja4">
                   <void property="comprador">
                    <object idref="Comprador0"/>
                   </void>
                   <void property="dineroOfrecido">
                    <int>145</int>
                   </void>
                   <void property="publicacion">
                    <object idref="Publicacion1"/>
                   </void>
                  </object>
                 </void>
                 <void method="add">
                  <object idref="Puja0"/>
                 </void>
                </void>
               </object>
              </void>
              <void property="dineroOfrecido">
               <int>1451</int>
              </void>
              <void property="publicacion">
               <object idref="Publicacion1"/>
              </void>
             </object>
            </void>
            <void property="pujas">
             <void method="add">
              <object idref="Puja3"/>
             </void>
             <void method="add">
              <object idref="Puja4"/>
             </void>
             <void method="add">
              <object idref="Puja0"/>
             </void>
            </void>
            <void property="valorInicial">
             <int>10000</int>
            </void>
           </object>
          </void>
          <void method="add">
           <object class="co.edu.uniquindio.progiii.subastasquindio.model.Publicacion" id="Publicacion3">
            <void property="articulo">
             <object class="co.edu.uniquindio.progiii.subastasquindio.model.Articulo">
              <void property="descripcion">
               <string>Es la primera prueba para conocer si la imagen funciona</string>
              </void>
              <void property="foto">
               <string>/Users/nicolasjurado/Documents/GitHub/SubastasQuindio_Proyecto/src/co/edu/uniquindio/progiii/subastasquindio/view/images/LogoSubastasQuindio.png</string>
              </void>
              <void property="nombre">
               <string>PruebaImg1</string>
              </void>
              <void property="tipo">
               <object idref="TipoPublicacion4"/>
              </void>
              <void property="vendedor">
               <object idref="Vendedor0"/>
              </void>
             </object>
            </void>
            <void property="estado">
             <object idref="Estado0"/>
            </void>
            <void property="pujaGanadora">
             <object class="co.edu.uniquindio.progiii.subastasquindio.model.Puja" id="Puja5">
              <void property="comprador">
               <object class="co.edu.uniquindio.progiii.subastasquindio.model.Comprador" id="Comprador1">
                <void property="contrasena">
                 <string>1234</string>
                </void>
                <void property="edad">
                 <int>19</int>
                </void>
                <void property="email">
                 <string>nickjurado@mail.com</string>
                </void>
                <void property="nombreUsuario">
                 <string>NickJurado</string>
                </void>
                <void property="pujas">
                 <void method="add">
                  <object class="co.edu.uniquindio.progiii.subastasquindio.model.Puja" id="Puja6">
                   <void property="comprador">
                    <object idref="Comprador1"/>
                   </void>
                   <void property="dineroOfrecido">
                    <int>1</int>
                   </void>
                   <void property="publicacion">
                    <object class="co.edu.uniquindio.progiii.subastasquindio.model.Publicacion" id="Publicacion4">
                     <void property="articulo">
                      <object idref="Articulo1"/>
                     </void>
                     <void property="estado">
                      <object class="java.lang.Enum" method="valueOf">
                       <class>co.edu.uniquindio.progiii.subastasquindio.model.Estado</class>
                       <string>EN_ESPERA_PUJA_GANADORA</string>
                      </object>
                     </void>
                     <void property="pujaGanadora">
                      <object idref="Puja6"/>
                     </void>
                     <void property="pujas">
                      <void method="add">
                       <object class="co.edu.uniquindio.progiii.subastasquindio.model.Puja">
                        <void property="comprador">
                         <object idref="Comprador1"/>
                        </void>
                        <void property="dineroOfrecido">
                         <int>1</int>
                        </void>
                        <void property="publicacion">
                         <object idref="Publicacion4"/>
                        </void>
                       </object>
                      </void>
                      <void method="add">
                       <object class="co.edu.uniquindio.progiii.subastasquindio.model.Puja">
                        <void property="comprador">
                         <object idref="Comprador1"/>
                        </void>
                        <void property="dineroOfrecido">
                         <int>2</int>
                        </void>
                        <void property="publicacion">
                         <object idref="Publicacion4"/>
                        </void>
                       </object>
                      </void>
                      <void method="add">
                       <object idref="Puja6"/>
                      </void>
                      <void method="add">
                       <object class="co.edu.uniquindio.progiii.subastasquindio.model.Puja">
                        <void property="comprador">
                         <object idref="Comprador1"/>
                        </void>
                        <void property="dineroOfrecido">
                         <int>2</int>
                        </void>
                        <void property="publicacion">
                         <object idref="Publicacion4"/>
                        </void>
                       </object>
                      </void>
                      <void method="add">
                       <object class="co.edu.uniquindio.progiii.subastasquindio.model.Puja">
                        <void property="comprador">
                         <object idref="Comprador1"/>
                        </void>
                        <void property="dineroOfrecido">
                         <int>3</int>
                        </void>
                        <void property="publicacion">
                         <object idref="Publicacion4"/>
                        </void>
                       </object>
                      </void>
                      <void method="add">
                       <object class="co.edu.uniquindio.progiii.subastasquindio.model.Puja">
                        <void property="comprador">
                         <object idref="Comprador1"/>
                        </void>
                        <void property="dineroOfrecido">
                         <int>3</int>
                        </void>
                        <void property="publicacion">
                         <object idref="Publicacion4"/>
                        </void>
                       </object>
                      </void>
                      <void method="add">
                       <object class="co.edu.uniquindio.progiii.subastasquindio.model.Puja">
                        <void property="comprador">
                         <object idref="Comprador1"/>
                        </void>
                        <void property="dineroOfrecido">
                         <int>4</int>
                        </void>
                        <void property="publicacion">
                         <object idref="Publicacion4"/>
                        </void>
                       </object>
                      </void>
                     </void>
                     <void property="valorInicial">
                      <int>123</int>
                     </void>
                    </object>
                   </void>
                  </object>
                 </void>
                 <void method="add">
                  <object class="co.edu.uniquindio.progiii.subastasquindio.model.Puja" id="Puja7">
                   <void property="comprador">
                    <object idref="Comprador1"/>
                   </void>
                   <void property="dineroOfrecido">
                    <int>2000000</int>
                   </void>
                   <void property="publicacion">
                    <object class="co.edu.uniquindio.progiii.subastasquindio.model.Publicacion" id="Publicacion5">
                     <void property="articulo">
                      <object idref="Articulo4"/>
                     </void>
                     <void property="estado">
                      <object idref="Estado0"/>
                     </void>
                     <void property="fechaFinal">
                      <string>2022-11-05</string>
                     </void>
                     <void property="fechaInicial">
                      <string>2022-11-03</string>
                     </void>
                     <void property="pujaGanadora">
                      <object idref="Puja7"/>
                     </void>
                     <void property="pujas">
                      <void method="add">
                       <object idref="Puja7"/>
                      </void>
                     </void>
                     <void property="valorInicial">
                      <int>10000</int>
                     </void>
                    </object>
                   </void>
                  </object>
                 </void>
                </void>
               </object>
              </void>
              <void property="dineroOfrecido">
               <int>1</int>
              </void>
              <void property="publicacion">
               <object idref="Publicacion3"/>
              </void>
             </object>
            </void>
            <void property="pujas">
             <void method="add">
              <object idref="Puja5"/>
             </void>
            </void>
            <void property="valorInicial">
             <int>1</int>
            </void>
           </object>
          </void>
          <void method="add">
           <object class="co.edu.uniquindio.progiii.subastasquindio.model.Publicacion" id="Publicacion6">
            <void property="articulo">
             <object idref="Articulo2"/>
            </void>
            <void property="estado">
             <object idref="Estado0"/>
            </void>
            <void property="fechaFinal">
             <string>2022-12-04</string>
            </void>
            <void property="fechaInicial">
             <string>2022-11-11</string>
            </void>
            <void property="pujaGanadora">
             <object class="co.edu.uniquindio.progiii.subastasquindio.model.Puja">
              <void property="comprador">
               <object idref="Comprador1"/>
              </void>
              <void property="dineroOfrecido">
               <int>2200000</int>
              </void>
              <void property="publicacion">
               <object idref="Publicacion6"/>
              </void>
             </object>
            </void>
            <void property="pujas">
             <void method="add">
              <object class="co.edu.uniquindio.progiii.subastasquindio.model.Puja">
               <void property="comprador">
                <object idref="Comprador1"/>
               </void>
               <void property="dineroOfrecido">
                <int>10000</int>
               </void>
               <void property="publicacion">
                <object idref="Publicacion6"/>
               </void>
              </object>
             </void>
            </void>
            <void property="valorInicial">
             <int>10000</int>
            </void>
           </object>
          </void>
          <void method="add">
           <object idref="Publicacion5"/>
          </void>
         </void>
        </object>
       </void>
      </object>
     </void>
     <void property="estado">
      <object idref="Estado1"/>
     </void>
     <void property="pujas">
      <void method="add">
       <object class="co.edu.uniquindio.progiii.subastasquindio.model.Puja" id="Puja8">
        <void property="comprador">
         <object class="co.edu.uniquindio.progiii.subastasquindio.model.Comprador" id="Comprador2">
          <void property="contrasena">
           <string>1234</string>
          </void>
          <void property="edad">
           <int>1234</int>
          </void>
          <void property="email">
           <string>camilo@mail.com</string>
          </void>
          <void property="nombreUsuario">
           <string>Camilo</string>
          </void>
          <void property="pujas">
           <void method="add">
            <object idref="Puja8"/>
           </void>
           <void method="add">
            <object class="co.edu.uniquindio.progiii.subastasquindio.model.Puja" id="Puja9">
             <void property="comprador">
              <object idref="Comprador2"/>
             </void>
             <void property="dineroOfrecido">
              <int>3</int>
             </void>
             <void property="publicacion">
              <object class="co.edu.uniquindio.progiii.subastasquindio.model.Publicacion" id="Publicacion7">
               <void property="articulo">
                <object class="co.edu.uniquindio.progiii.subastasquindio.model.Articulo" id="Articulo5">
                 <void property="descripcion">
                  <string>Es un arroz nigga</string>
                 </void>
                 <void property="nombre">
                  <string>Arroz Negro</string>
                 </void>
                 <void property="tipo">
                  <object idref="TipoPublicacion1"/>
                 </void>
                 <void property="vendedor">
                  <object class="co.edu.uniquindio.progiii.subastasquindio.model.Vendedor" id="Vendedor1">
                   <void property="articulos">
                    <void method="add">
                     <object idref="Articulo5"/>
                    </void>
                   </void>
                   <void property="contrasena">
                    <string>1234</string>
                   </void>
                   <void property="edad">
                    <int>35</int>
                   </void>
                   <void property="email">
                    <string>@</string>
                   </void>
                   <void property="id">
                    <string>1</string>
                   </void>
                   <void property="nombreUsuario">
                    <string>JuanVende</string>
                   </void>
                   <void property="publicaciones">
                    <void method="add">
                     <object idref="Publicacion7"/>
                    </void>
                   </void>
                  </object>
                 </void>
                </object>
               </void>
               <void property="estado">
                <object idref="Estado0"/>
               </void>
               <void property="pujaGanadora">
                <object class="co.edu.uniquindio.progiii.subastasquindio.model.Puja" id="Puja10">
                 <void property="comprador">
                  <object idref="Comprador1"/>
                 </void>
                 <void property="dineroOfrecido">
                  <int>3</int>
                 </void>
                 <void property="publicacion">
                  <object idref="Publicacion7"/>
                 </void>
                </object>
               </void>
               <void property="pujas">
                <void method="add">
                 <object class="co.edu.uniquindio.progiii.subastasquindio.model.Puja">
                  <void property="comprador">
                   <object idref="Comprador1"/>
                  </void>
                  <void property="dineroOfrecido">
                   <int>1</int>
                  </void>
                  <void property="publicacion">
                   <object idref="Publicacion7"/>
                  </void>
                 </object>
                </void>
                <void method="add">
                 <object class="co.edu.uniquindio.progiii.subastasquindio.model.Puja">
                  <void property="comprador">
                   <object idref="Comprador1"/>
                  </void>
                  <void property="dineroOfrecido">
                   <int>2</int>
                  </void>
                  <void property="publicacion">
                   <object idref="Publicacion7"/>
                  </void>
                 </object>
                </void>
                <void method="add">
                 <object idref="Puja10"/>
                </void>
                <void method="add">
                 <object idref="Puja9"/>
                </void>
               </void>
               <void property="valorInicial">
                <int>1</int>
               </void>
              </object>
             </void>
            </object>
           </void>
          </void>
         </object>
        </void>
        <void property="dineroOfrecido">
         <int>1</int>
        </void>
        <void property="publicacion">
         <object idref="Publicacion0"/>
        </void>
       </object>
      </void>
     </void>
     <void property="valorInicial">
      <int>1</int>
     </void>
    </object>
   </void>
   <void method="add">
    <object idref="Publicacion7"/>
   </void>
   <void method="add">
    <object idref="Publicacion1"/>
   </void>
   <void method="add">
    <object idref="Publicacion3"/>
   </void>
   <void method="add">
    <object idref="Publicacion6"/>
   </void>
   <void method="add">
    <object class="co.edu.uniquindio.progiii.subastasquindio.model.Publicacion" id="Publicacion8">
     <void property="articulo">
      <object class="co.edu.uniquindio.progiii.subastasquindio.model.Articulo" id="Articulo6">
       <void property="descripcion">
        <string>23</string>
       </void>
       <void property="foto">
        <string>/Users/nicolasjurado/Documents/GitHub/SubastasQuindio_Proyecto/src/co/edu/uniquindio/progiii/subastasquindio/view/images/LogoSubastasQuindio.png</string>
       </void>
       <void property="nombre">
        <string>1</string>
       </void>
       <void property="tipo">
        <object idref="TipoPublicacion2"/>
       </void>
       <void property="vendedor">
        <object class="co.edu.uniquindio.progiii.subastasquindio.model.Vendedor" id="Vendedor2">
         <void property="articulos">
          <void method="add">
           <object idref="Articulo6"/>
          </void>
         </void>
         <void property="contrasena">
          <string>1234</string>
         </void>
         <void property="edad">
          <int>43</int>
         </void>
         <void property="email">
          <string>vededor@mail.co</string>
         </void>
         <void property="id">
          <string>1234</string>
         </void>
         <void property="nombreUsuario">
          <string>VendedorPrueba1</string>
         </void>
         <void property="publicaciones">
          <void method="add">
           <object idref="Publicacion8"/>
          </void>
         </void>
        </object>
       </void>
      </object>
     </void>
     <void property="estado">
      <object idref="Estado0"/>
     </void>
     <void property="fechaFinal">
      <string>2022-11-27</string>
     </void>
     <void property="fechaInicial">
      <string>2022-11-10</string>
     </void>
     <void property="pujaGanadora">
      <object class="co.edu.uniquindio.progiii.subastasquindio.model.Puja">
       <void property="comprador">
        <object idref="Comprador1"/>
       </void>
       <void property="dineroOfrecido">
        <int>20000</int>
       </void>
       <void property="publicacion">
        <object idref="Publicacion8"/>
       </void>
      </object>
     </void>
     <void property="pujas">
      <void method="add">
       <object class="co.edu.uniquindio.progiii.subastasquindio.model.Puja">
        <void property="comprador">
         <object idref="Comprador1"/>
        </void>
        <void property="dineroOfrecido">
         <int>10000</int>
        </void>
        <void property="publicacion">
         <object idref="Publicacion8"/>
        </void>
       </object>
      </void>
     </void>
     <void property="valorInicial">
      <int>100000</int>
     </void>
    </object>
   </void>
   <void method="add">
    <object idref="Publicacion5"/>
   </void>
  </void>
  <void property="listaUsuarios">
   <void method="add">
    <object class="co.edu.uniquindio.progiii.subastasquindio.model.Comprador">
     <void property="contrasena">
      <string>1234</string>
     </void>
     <void property="edad">
      <int>1234</int>
     </void>
     <void property="email">
      <string>joshVende@mail</string>
     </void>
     <void property="nombreUsuario">
      <string>JoshVende</string>
     </void>
    </object>
   </void>
   <void method="add">
    <object idref="Vendedor0"/>
   </void>
   <void method="add">
    <object idref="Vendedor1"/>
   </void>
   <void method="add">
    <object class="co.edu.uniquindio.progiii.subastasquindio.model.Vendedor" id="Vendedor3">
     <void property="articulos">
      <void method="add">
       <object class="co.edu.uniquindio.progiii.subastasquindio.model.Articulo" id="Articulo7">
        <void property="descripcion">
         <string>Es un pan</string>
        </void>
        <void property="nombre">
         <string>Pan</string>
        </void>
        <void property="tipo">
         <object idref="TipoPublicacion1"/>
        </void>
        <void property="vendedor">
         <object idref="Vendedor3"/>
        </void>
       </object>
      </void>
      <void method="add">
       <object class="co.edu.uniquindio.progiii.subastasquindio.model.Articulo" id="Articulo8">
        <void property="descripcion">
         <string>MacBook Pro nueva </string>
        </void>
        <void property="nombre">
         <string>MacBook Pro</string>
        </void>
        <void property="tipo">
         <object idref="TipoPublicacion4"/>
        </void>
        <void property="vendedor">
         <object idref="Vendedor3"/>
        </void>
       </object>
      </void>
     </void>
     <void property="contrasena">
      <string>1234</string>
     </void>
     <void property="edad">
      <int>58</int>
     </void>
     <void property="email">
      <string>nicoVende@mail.com</string>
     </void>
     <void property="id">
      <string>1234</string>
     </void>
     <void property="nombreUsuario">
      <string>NicoVende</string>
     </void>
     <void property="publicaciones">
      <void method="add">
       <object class="co.edu.uniquindio.progiii.subastasquindio.model.Publicacion">
        <void property="articulo">
         <object idref="Articulo7"/>
        </void>
        <void property="estado">
         <object idref="Estado1"/>
        </void>
        <void property="valorInicial">
         <int>500</int>
        </void>
       </object>
      </void>
      <void method="add">
       <object class="co.edu.uniquindio.progiii.subastasquindio.model.Publicacion">
        <void property="articulo">
         <object idref="Articulo8"/>
        </void>
        <void property="estado">
         <object class="java.lang.Enum" method="valueOf">
          <class>co.edu.uniquindio.progiii.subastasquindio.model.Estado</class>
          <string>INACTIVO</string>
         </object>
        </void>
        <void property="valorInicial">
         <int>3000000</int>
        </void>
       </object>
      </void>
     </void>
    </object>
   </void>
   <void method="add">
    <object class="co.edu.uniquindio.progiii.subastasquindio.model.Vendedor">
     <void property="contrasena">
      <string>Zeus</string>
     </void>
     <void property="edad">
      <int>19</int>
     </void>
     <void property="email">
      <string>miguel.vargas@</string>
     </void>
     <void property="id">
      <string>1001300748</string>
     </void>
     <void property="nombreUsuario">
      <string>miguel</string>
     </void>
    </object>
   </void>
   <void method="add">
    <object idref="Comprador1"/>
   </void>
   <void method="add">
    <object idref="Comprador2"/>
   </void>
   <void method="add">
    <object class="co.edu.uniquindio.progiii.subastasquindio.model.Vendedor" id="Vendedor4">
     <void property="articulos">
      <void method="add">
       <object class="co.edu.uniquindio.progiii.subastasquindio.model.Articulo">
        <void property="descripcion">
         <string>Descripcion del articulo</string>
        </void>
        <void property="nombre">
         <string>Articulo de ejemplo</string>
        </void>
        <void property="tipo">
         <object idref="TipoPublicacion3"/>
        </void>
        <void property="vendedor">
         <object idref="Vendedor4"/>
        </void>
       </object>
      </void>
     </void>
     <void property="contrasena">
      <string>123</string>
     </void>
     <void property="edad">
      <int>20</int>
     </void>
     <void property="email">
      <string>123@gmail.com</string>
     </void>
     <void property="id">
      <string>191919</string>
     </void>
     <void property="nombreUsuario">
      <string>VendedorEjemplo</string>
     </void>
    </object>
   </void>
   <void method="add">
    <object class="co.edu.uniquindio.progiii.subastasquindio.model.Vendedor" id="Vendedor5">
     <void property="articulos">
      <void method="add">
       <object class="co.edu.uniquindio.progiii.subastasquindio.model.Articulo">
        <void property="descripcion">
         <string>Articulo de prueba para el video</string>
        </void>
        <void property="nombre">
         <string>ArticuloVideo</string>
        </void>
        <void property="tipo">
         <object idref="TipoPublicacion0"/>
        </void>
        <void property="vendedor">
         <object idref="Vendedor5"/>
        </void>
       </object>
      </void>
     </void>
     <void property="contrasena">
      <string>123</string>
     </void>
     <void property="edad">
      <int>20</int>
     </void>
     <void property="email">
      <string>vendedor@gmail.com</string>
     </void>
     <void property="id">
      <string>111</string>
     </void>
     <void property="nombreUsuario">
      <string>VendedorTest</string>
     </void>
    </object>
   </void>
   <void method="add">
    <object idref="Comprador0"/>
   </void>
   <void method="add">
    <object idref="Vendedor2"/>
   </void>
  </void>
  <void property="publicacionSeleccionada">
   <object idref="Publicacion5"/>
  </void>
  <void property="usuarioLogeado">
   <object idref="Comprador1"/>
  </void>
 </object>
</java>
